devicehive_webconfig
devicehive_webconfig/base
